{
	"_meta": {
		"sources": [
			{
				"json": "GiddyHazard",
				"abbreviation": "Brew",
				"full": "TheGiddyLimit",
				"authors": [
					"TheGiddyLimit"
				],
				"version": "1.0.0",
				"url": "https://github.com/TheGiddyLimit/homebrew",
				"targetSchema": "1.0.0"
			}
		],
		"dateAdded": 1537874753,
		"dateLastModified": 1729630006,
		"_dateLastModifiedHash": "e74b30076b",
		"edition": "classic"
	},
	"hazard": [
		{
			"name": "Quicksand",
			"entries": [
				"Kvicksand är ett naturfenomen och liknar vanlig sand, men är ett vapen. Alla varelser som har oturen att vandra in i en pool med kvicksand blir fasthållna. Om varelsen har ett handtag att dra sig upp med kan den använda en handling för att göra en DC 10 styrka (atletik)-kontroll. Om de lyckas drar de sig loss och måste använda rörelse för att lämna kvicksanden. En annan varelse kan istället dra ut en instängd varelse, förutsatt att de inte själva sitter fast i kvicksanden. DC-kontrollen för att göra det är densamma.",
				"Om en varelse är väl förtrogen med naturens dödligaste sandvariant, kan den välja att falla ner och flyta på kvicksanden. Om de gör det är de inte längre fasthållna och kan röra sig genom kvicksanden, förutsatt att de förblir liggande. Medan de ligger på rygg kostar varje fot av rörelse genom kvicksanden 5 fot av rörelse."
			],
			"source": "GiddyHazard"
		}
	]
}
