{
	"_meta": {
		"sources": [
			{
				"json": "mfovc",
				"abbreviation": "MFoV",
				"full": "Middle Finger of Vecna: Craftsman",
				"authors": [
					"Middle Finger of Vecna"
				],
				"convertedBy": [
					"BioOnPC"
				],
				"version": "2.4",
				"url": "http://mfov.magehandpress.com/2017/04/craftsman-redux.html",
				"targetSchema": "1.0.0"
			}
		],
		"dateAdded": 1530561900,
		"dateLastModified": 1729630006,
		"_dateLastModifiedHash": "95a2117c8b",
		"edition": "classic"
	},
	"class": [
		{
			"name": "Craftsman",
			"source": "mfovc",
			"hd": {
				"number": 1,
				"faces": 10
			},
			"proficiency": [
				"int",
				"con"
			],
			"classTableGroups": [
				{
					"colLabels": [
						""
					],
					"rows": [
						[
							""
						],
						[
							""
						],
						[
							""
						],
						[
							""
						],
						[
							""
						],
						[
							""
						],
						[
							""
						],
						[
							""
						],
						[
							""
						],
						[
							""
						],
						[
							""
						],
						[
							""
						],
						[
							""
						],
						[
							""
						],
						[
							""
						],
						[
							""
						],
						[
							""
						],
						[
							""
						],
						[
							""
						],
						[
							""
						]
					]
				}
			],
			"startingProficiencies": {
				"armor": [
					"light",
					"medium",
					"heavy",
					"shield"
				],
				"weapons": [
					"simple",
					"martial"
				],
				"tools": [
					"all artisan's tools"
				],
				"skills": [
					{
						"choose": {
							"from": [
								"arcana",
								"athletics",
								"history",
								"investigation",
								"medicine",
								"perception",
								"persuasion"
							],
							"count": 2
						}
					}
				]
			},
			"startingEquipment": {
				"additionalFromBackground": true,
				"default": [
					"A {@item shield} and (a) {@item chain mail} or (b) {@item scale mail}",
					"A {@item dagger} and (a) a {@item warhammer} or (b) any simple weapon",
					"(a) a {@item light crossbow} and {@item crossbow bolts (20)|phb|20 bolts} or (b) a {@item shortbow} and {@item arrows (20)|phb|20 arrows}",
					"craftsman's tools and (a) an {@item explorer's pack} or (b) one kit you're proficient with"
				],
				"defaultData": [
					{
						"A {@item shield} and": [],
						"{@item chain mail} or": []
					},
					{
						"A {@item dagger} and": [],
						"a {@item warhammer} or": []
					},
					{
						"a": [
							"light crossbow",
							"crossbow bolts (20)|phb"
						],
						"b": [
							"shortbow",
							"arrows (20)|phb"
						]
					},
					{
						"craftsman's tools and": [],
						"an {@item explorer's pack} or": []
					}
				]
			},
			"classFeatures": [
				"Bonus Proficiencies|Craftsman|mfovc|1",
				"Smithy|Craftsman|mfovc|1",
				{
					"classFeature": "Metallurgy|Craftsman|mfovc|2",
					"gainSubclassFeature": true
				},
				"Tool Belt|Craftsman|mfovc|2",
				{
					"classFeature": "Profession|Craftsman|mfovc|3",
					"gainSubclassFeature": true
				},
				"Ability Score Improvement|Craftsman|mfovc|4",
				"Extra Attack|Craftsman|mfovc|5",
				"Folded Steel|Craftsman|mfovc|6",
				{
					"classFeature": "Apprentice Techniques|Craftsman|mfovc|6",
					"gainSubclassFeature": true
				},
				{
					"classFeature": "Profession Feature|Craftsman|mfovc|7",
					"gainSubclassFeature": true
				},
				"Ability Score Improvement|Craftsman|mfovc|8",
				"Layman's Modifications|Craftsman|mfovc|9",
				{
					"classFeature": "Journeyman Techniques|Craftsman|mfovc|9",
					"gainSubclassFeature": true
				},
				{
					"classFeature": "Profession Feature|Craftsman|mfovc|10",
					"gainSubclassFeature": true
				},
				"Craftman's Strike|Craftsman|mfovc|11",
				"Ability Score Improvement|Craftsman|mfovc|12",
				{
					"classFeature": "Master Techniques|Craftsman|mfovc|13",
					"gainSubclassFeature": true
				},
				{
					"classFeature": "Profession Feature|Craftsman|mfovc|14",
					"gainSubclassFeature": true
				},
				"Uncanny Tool Belt|Craftsman|mfovc|15",
				"Ability Score Improvement|Craftsman|mfovc|16",
				{
					"classFeature": "Legendary Techniques|Craftsman|mfovc|17",
					"gainSubclassFeature": true
				},
				{
					"classFeature": "Profession Feature|Craftsman|mfovc|18",
					"gainSubclassFeature": true
				},
				"Ability Score Improvement|Craftsman|mfovc|19",
				"Magnum Opus|Craftsman|mfovc|20"
			],
			"subclassTitle": "Professions"
		}
	],
	"itemProperty": [
		{
			"abbreviation": "EX",
			"source": "mfovc",
			"page": 0,
			"entries": [
				{
					"type": "entries",
					"name": "Exotic",
					"entries": [
						"Las armas, armaduras y escudos exóticos son piezas de equipo que requieren un increíble nivel de habilidad para manejarlas o llevarlas correctamente, ya que a menudo son inusualmente pesadas, extrañamente equilibradas o de extraña construcción. Por lo tanto, ninguna otra clase que no sea el artesano adquiere competencia con las armas o armaduras exóticas. Para obtener competencia con una pieza de equipo exótico, debes realizar la proeza Dominio exótico."
					]
				}
			]
		},
		{
			"abbreviation": "CO",
			"source": "mfovc",
			"page": 0,
			"entries": [
				{
					"type": "entries",
					"name": "Collapsible",
					"entries": [
						"Esta arma tiene partes huecas, normalmente en la empuñadura, que te permiten replegarla sobre sí misma para facilitar su almacenamiento y ocultación. Mientras esté guardada, tienes ventaja en los chequeos de Destreza (Sigilo) realizados para ocultar esta arma."
					]
				}
			]
		},
		{
			"abbreviation": "DO",
			"source": "mfovc",
			"page": 0,
			"entries": [
				{
					"type": "entries",
					"name": "Double",
					"entries": [
						"Esta arma tiene dos extremos que infligen daño. Mientras la manejas, se te trata como si estuvieras manejando dos armas y, al participar en un combate con dos armas, puedes usar cualquiera de los extremos del arma para realizar ataques adicionales."
					]
				}
			]
		},
		{
			"abbreviation": "MA",
			"source": "mfovc",
			"page": 0,
			"entries": [
				{
					"type": "entries",
					"name": "Massive",
					"entries": [
						"Esta arma es increíblemente grande y pesada. Cuando una criatura empuña esta arma, reduce en uno el número de ataques que esa criatura puede realizar con la acción de Ataque, hasta un mínimo de uno."
					]
				}
			]
		},
		{
			"abbreviation": "MO",
			"source": "mfovc",
			"page": 0,
			"entries": [
				{
					"type": "entries",
					"name": "Mounted",
					"entries": [
						"Esta arma se utiliza normalmente mientras está sujeta a un trípode, carro u otra montura de apoyo. Mientras está montada, no se puede mover. Puedes montar o desmontar esta arma como acción. Mientras no esté montada y la criatura que la empuña no esté en posición prona, esta arma sólo puede ser utilizada con destreza por una criatura mediana o mayor con una puntuación de Fuerza de al menos 17."
					]
				}
			]
		},
		{
			"abbreviation": "RE",
			"source": "mfovc",
			"page": 0,
			"entries": [
				{
					"type": "entries",
					"name": "Returning",
					"entries": [
						"Cuando lanzas esta arma, puedes hacer un chequeo de Atletismo DC 15. Si tienes éxito, el arma vuelve a tu mano al final de tu turno."
					]
				}
			]
		},
		{
			"abbreviation": "SH",
			"source": "mfovc",
			"page": 0,
			"entries": [
				{
					"type": "entries",
					"name": "Shield",
					"entries": [
						"Esta arma es lo suficientemente grande o tiene una forma determinada para que puedas utilizarla para protegerte del daño. Mientras empuñes esta arma y no lleves un escudo, ganas un +1 a tu CA. Sólo puedes obtener el beneficio de un arma con esta propiedad a la vez."
					]
				}
			]
		},
		{
			"abbreviation": "SU",
			"source": "mfovc",
			"page": 0,
			"entries": [
				{
					"type": "entries",
					"name": "Superheavy",
					"entries": [
						"Esta arma es inusualmente grande para su tipo. Debes tener una puntuación de Fuerza de al menos 17 para manejar con destreza un arma superpesada. Las criaturas de tamaño inferior a Meduim no pueden manejar un arma superpesada, independientemente de su puntuación de Fuerza. Esta propiedad también cuenta como la propiedad Heavy."
					]
				}
			]
		},
		{
			"abbreviation": "SW",
			"source": "mfovc",
			"page": 0,
			"entries": [
				{
					"type": "entries",
					"name": "Switch",
					"entries": [
						"Esta arma tiene dos formas. El daño y las propiedades de su segunda forma se indican más arriba. Puedes usar una acción de bonificación para cambiar entre estas formas."
					]
				}
			]
		}
	],
	"item": [
		{
			"name": "Asp",
			"type": "M",
			"weaponCategory": "exotic",
			"rarity": "none",
			"value": 5000,
			"weight": 1,
			"dmg1": "1d4",
			"dmgType": "B",
			"property": [
				"EX",
				"CO",
				"F",
				"L",
				"T"
			],
			"range": "20/60",
			"source": "mfovc"
		},
		{
			"name": "Battle Plate",
			"type": "HA",
			"rarity": "none",
			"value": 200000,
			"weight": 75,
			"ac": 19,
			"strength": "16",
			"stealth": true,
			"source": "mfovc",
			"entries": [
				"La placa de batalla, más resistente que la placa completa, consiste en un traje completo de placas entrelazadas con una capa de cuero grueso y cadena por debajo."
			]
		},
		{
			"name": "Chakram",
			"type": "M",
			"weaponCategory": "exotic",
			"rarity": "none",
			"value": 2500,
			"weight": 1,
			"dmg1": "1d6",
			"dmgType": "S",
			"property": [
				"EX",
				"CO",
				"F",
				"L",
				"T"
			],
			"range": "30/120",
			"source": "mfovc"
		},
		{
			"name": "Craftsman's Tools",
			"type": "AT",
			"rarity": "none",
			"value": 7500,
			"weight": 20,
			"source": "mfovc",
			"entries": [
				"Una caja de herramientas combinada que cubre lo esencial de todas las herramientas del artesano y le permite añadir su bonificación de competencia a cualquier cosa que fabrique."
			]
		},
		{
			"name": "Dervish",
			"type": "M",
			"weaponCategory": "exotic",
			"rarity": "none",
			"value": 15000,
			"weight": 1,
			"dmg1": "1d6",
			"dmgType": "S",
			"property": [
				"EX",
				"DO",
				"F",
				"L",
				"2H"
			],
			"entries": [
				{
					"type": "inset",
					"name": "Double Damage",
					"entries": [
						"{@dice 1d6} de corte"
					]
				}
			],
			"source": "mfovc"
		},
		{
			"name": "Double-Sword",
			"type": "M",
			"weaponCategory": "exotic",
			"rarity": "none",
			"value": 20000,
			"weight": 10,
			"dmg1": "1d8",
			"dmgType": "S",
			"property": [
				"EX",
				"DO",
				"H",
				"2H"
			],
			"entries": [
				{
					"type": "inset",
					"name": "Double Damage",
					"entries": [
						"{@dice 1d8} de corte"
					]
				}
			],
			"source": "mfovc"
		},
		{
			"name": "Dwarven Waraxe",
			"type": "M",
			"weaponCategory": "exotic",
			"rarity": "none",
			"value": 20000,
			"weight": 12,
			"dmg1": "1d8",
			"dmgType": "S",
			"property": [
				"EX",
				"DO",
				"H",
				"2H"
			],
			"entries": [
				{
					"type": "inset",
					"name": "Double Damage",
					"entries": [
						"{@dice 1d8} perforación"
					]
				}
			],
			"source": "mfovc"
		},
		{
			"name": "Goliath Hammer",
			"type": "M",
			"weaponCategory": "exotic",
			"rarity": "none",
			"value": 15000,
			"weight": 20,
			"dmg1": "2d8",
			"dmgType": "B",
			"property": [
				"EX",
				"SU",
				"2H"
			],
			"source": "mfovc"
		},
		{
			"name": "Grand Spear",
			"type": "M",
			"weaponCategory": "exotic",
			"rarity": "none",
			"value": 15000,
			"weight": 10,
			"dmg1": "1d8",
			"dmg2": "1d10",
			"dmgType": "P",
			"property": [
				"EX",
				"T",
				"V"
			],
			"range": "20/60",
			"source": "mfovc"
		},
		{
			"name": "Great Scimitar",
			"type": "M",
			"weaponCategory": "exotic",
			"rarity": "none",
			"value": 35000,
			"weight": 4,
			"dmg1": "1d8",
			"dmg2": "1d10",
			"dmgType": "S",
			"property": [
				"EX",
				"F",
				"V"
			],
			"source": "mfovc"
		},
		{
			"name": "Greatbow",
			"type": "R",
			"weaponCategory": "exotic",
			"rarity": "none",
			"value": 20000,
			"weight": 15,
			"dmg1": "1d10",
			"dmgType": "P",
			"property": [
				"EX",
				"A",
				"SU",
				"2H"
			],
			"range": "150/600",
			"source": "mfovc",
			"ammoType": "arrow|phb"
		},
		{
			"name": "Hardened Leather",
			"type": "LA",
			"rarity": "none",
			"value": 50000,
			"weight": 15,
			"ac": 13,
			"source": "mfovc",
			"entries": [
				"Aunque su material es similar al de la armadura de cuero, el cuero endurecido añade una capa adicional de laca, que endurece el cuero hasta alcanzar una resistencia casi similar a la del hierro."
			]
		},
		{
			"name": "Hero Plate",
			"type": "MA",
			"rarity": "none",
			"value": 150000,
			"weight": 50,
			"ac": 16,
			"stealth": true,
			"source": "mfovc",
			"entries": [
				"Aunque no es sustancialmente más pesada ni más engorrosa que la media placa, la placa de héroe es ciertamente más impresionante: los grandes pauldrons, el casco alado y los adornos se suman a la inspiradora protección que proporciona esta armadura."
			]
		},
		{
			"name": "Mountain Cleaver",
			"type": "M",
			"weaponCategory": "exotic",
			"rarity": "none",
			"value": 25000,
			"weight": 45,
			"dmg1": "2d12",
			"dmgType": "S",
			"property": [
				"EX",
				"MA",
				"SU",
				"2H"
			],
			"source": "mfovc"
		},
		{
			"name": "Mountain Plate",
			"type": "HA",
			"rarity": "none",
			"value": 300000,
			"weight": 100,
			"ac": 20,
			"stealth": true,
			"source": "mfovc",
			"entries": [
				"Las placas de montaña, casi demasiado pesadas e incómodas de llevar, incluso para los guerreros más fuertes, consisten en un traje de armadura de placas de varios centímetros de grosor con un casco, guanteletes y botas atornillados. Ponerse la armadura de montaña lleva casi 15 minutos y requiere encajar una serie de abrazaderas y cierres de alta resistencia. La placa de montaña es excepcionalmente grande y pesada: requiere una fuerza de 18 para llevarla, no puede ser usada por criaturas de tamaño inferior al mediano y reduce la velocidad de marcha en 1,5 metros, independientemente de la puntuación de fuerza."
			]
		},
		{
			"name": "Portable Ballista",
			"type": "R",
			"weaponCategory": "exotic",
			"rarity": "none",
			"value": 45000,
			"weight": 25,
			"dmg1": "1d12",
			"dmgType": "P",
			"property": [
				"EX",
				"A",
				"LD",
				"MO",
				"SU",
				"2H"
			],
			"range": "200/800",
			"source": "mfovc"
		},
		{
			"name": "Quickblade",
			"type": "M",
			"weaponCategory": "exotic",
			"rarity": "none",
			"value": 5000,
			"weight": 1,
			"dmg1": "1d4",
			"dmgType": "P",
			"property": [
				"EX",
				"CO",
				"F",
				"L",
				"T"
			],
			"range": "20/60",
			"source": "mfovc"
		},
		{
			"name": "Shield Axe",
			"type": "M",
			"weaponCategory": "exotic",
			"rarity": "none",
			"value": 10000,
			"weight": 5,
			"dmg1": "1d6",
			"dmgType": "S",
			"property": [
				"EX",
				"SH"
			],
			"source": "mfovc"
		},
		{
			"name": "Spiked Chain",
			"type": "M",
			"weaponCategory": "exotic",
			"rarity": "none",
			"value": 10000,
			"weight": 6,
			"dmg1": "1d4",
			"dmgType": "S",
			"property": [
				"EX",
				"DO",
				"F",
				"R",
				"2H"
			],
			"entries": [
				{
					"type": "inset",
					"name": "Double Damage",
					"entries": [
						"{@dice 1d4} de corte"
					]
				}
			],
			"source": "mfovc"
		},
		{
			"name": "Tether Club",
			"type": "M",
			"weaponCategory": "exotic",
			"rarity": "none",
			"value": 15000,
			"weight": 4,
			"dmg1": "1d8",
			"dmgType": "B",
			"property": [
				"EX",
				"F",
				"SW"
			],
			"entries": [
				{
					"type": "inset",
					"name": "Switch Stats",
					"entries": [
						"{@dice 1d6} Golpear, delicadeza, alcance"
					]
				}
			],
			"source": "mfovc"
		},
		{
			"name": "Titan Maul",
			"type": "M",
			"weaponCategory": "exotic",
			"rarity": "none",
			"value": 20000,
			"weight": 45,
			"dmg1": "2d12",
			"dmgType": "B",
			"property": [
				"EX",
				"MA",
				"SU",
				"2H"
			],
			"source": "mfovc"
		},
		{
			"name": "Tower Shield",
			"type": "S",
			"rarity": "none",
			"value": 15000,
			"weight": 20,
			"ac": 3,
			"strength": "18",
			"source": "mfovc",
			"entries": [
				"Mucho más grande que un escudo normal, un escudo de torre es un tablón grande, generalmente rectangular, de madera gruesa o metal, suficiente para cubrir casi todo el cuerpo."
			]
		},
		{
			"name": "Wall Shield",
			"type": "S",
			"rarity": "none",
			"value": 10000,
			"weight": 15,
			"ac": 2,
			"strength": "16",
			"source": "mfovc",
			"entries": [
				"Aún más grande que el escudo de torre, el escudo de pared es un enorme escudo del tamaño de una puerta con un conjunto de imponentes pinchos colocados en el borde inferior, orientados hacia el suelo. Es mucho más engorroso de usar y resulta un poco menos eficaz que el escudo de torre en el combate cuerpo a cuerpo normal. Los pinchos de la fila inferior sirven para anclar el escudo al suelo: como acción, puedes golpear el escudo contra el suelo y apuntalarte tras él. Mientras está anclado de esta manera, un escudo de pared deja de otorgarte una bonificación a la CA y, en su lugar, proporciona una cobertura completa para una criatura de tamaño medio."
			]
		},
		{
			"name": "Warpike",
			"type": "M",
			"weaponCategory": "exotic",
			"rarity": "none",
			"value": 15000,
			"weight": 15,
			"dmg1": "1d12",
			"dmgType": "P",
			"property": [
				"EX",
				"R",
				"SU",
				"2H"
			],
			"source": "mfovc"
		},
		{
			"name": "Whipsword",
			"type": "M",
			"weaponCategory": "exotic",
			"rarity": "none",
			"value": 30000,
			"weight": 4,
			"dmg1": "1d8",
			"dmgType": "P",
			"property": [
				"EX",
				"F",
				"SW"
			],
			"entries": [
				{
					"type": "inset",
					"name": "Switch Stats",
					"entries": [
						"{@dice 1d6} tajo, delicadeza, alcance"
					]
				}
			],
			"source": "mfovc"
		},
		{
			"name": "Zweihänder",
			"type": "M",
			"weaponCategory": "exotic",
			"rarity": "none",
			"value": 15000,
			"weight": 15,
			"dmg1": "2d8",
			"dmgType": "S",
			"property": [
				"EX",
				"SU",
				"2H"
			],
			"source": "mfovc"
		}
	],
	"classFeature": [
		{
			"name": "Bonus Proficiencies",
			"source": "mfovc",
			"className": "Craftsman",
			"classSource": "mfovc",
			"level": 1,
			"entries": [
				"A partir del 1er nivel, eres competente con las armas y armaduras exóticas. También eres competente con todos los conjuntos de herramientas de artesano."
			]
		},
		{
			"name": "Smithy",
			"source": "mfovc",
			"className": "Craftsman",
			"classSource": "mfovc",
			"level": 1,
			"entries": [
				"A 1er nivel, llevas un conjunto de herramientas de artesano, una caja de herramientas combinada que cubre lo esencial de todas las herramientas de artesano y te permite añadir tu bonificación de competencia a cualquier cosa que hagas. Pesa 20 libras y puede ser reemplazado por 75 gp.",
				"Mientras utilizas estas herramientas para fabricar un objeto, puedes hacer el progreso de un día de fabricación en las 8 horas que dura un descanso largo. Cada día, puedes fabricar objetos con un valor total de 50 gp por tu nivel de artesano. Como es normal, debes proporcionar material por la mitad del valor de mercado de los objetos.",
				"Los objetos que elaboras también son de mayor calidad que los objetos normales de su tipo: añades tu modificador de Inteligencia + tu nivel de artesano al umbral de daño y a los PV de cualquier objeto que elabores."
			]
		},
		{
			"name": "Metallurgy",
			"source": "mfovc",
			"className": "Craftsman",
			"classSource": "mfovc",
			"level": 2,
			"entries": [
				"A 2º nivel, empiezas a aprender las complejidades más profundas de la artesanía de armas y armaduras.",
				{
					"type": "entries",
					"name": "Masterwork Equipment",
					"entries": [
						"Puedes forjar armas y armaduras de calidad magistral. Puedes fabricar un arma o una armadura de obra maestra gastando 100 gp en tiempo y materiales, además del coste normal necesario para fabricar el objeto. Un arma magistral tiene un bonificador de +1 a las tiradas de ataque y daño y una armadura magistral proporciona un bonificador de +1 a la CA mientras se lleva puesta. Además, los objetos de maestría pueden modificarse con técnicas de artesanía.",
						"No puedes construir una versión magistral de un arma exótica o una armadura exótica."
					]
				},
				{
					"type": "table",
					"caption": "Crafting Techniques Cost",
					"colLabels": [
						"Technique Level",
						"Craftsman Level",
						"Cost",
						"Crafting Time"
					],
					"colStyles": [
						"col-1",
						"col-1 text-center",
						"col-1 text-center",
						"col-1 text-center"
					],
					"rows": [
						[
							"Principiante",
							"2nd",
							"100 gp",
							"1 day"
						],
						[
							"Aprendiz",
							"6th",
							"200 gp",
							"3 day"
						],
						[
							"Journeyman",
							"9th",
							"300 gp",
							"5 day"
						],
						[
							"Maestro",
							"13th",
							"400 gp",
							"7 day"
						],
						[
							"Legendario",
							"17th",
							"500 gp",
							"14 day"
						]
					]
				},
				{
					"type": "entries",
					"name": "Crafting Techniques",
					"entries": [
						"Las técnicas de artesanía son modificaciones avanzadas que puedes hacer al equipo de trabajo maestro. Se dividen en 5 niveles: Principiante, Aprendiz, Oficial, Maestro y Legendario. A menos que se indique lo contrario, a una pieza de equipo de obra maestra sólo se le puede aplicar una técnica de artesanía de cada nivel. Una vez que una pieza de equipo maestro ha sido modificada, se ajusta a tus especificaciones exactas y sólo puedes utilizarla con destreza.",
						"Modificar una pieza de equipo de maestría requiere un coste en materiales, herramientas y tiempo, y sólo puede ser realizado por artesanos de un nivel suficientemente alto, como se muestra en la tabla de Coste de Técnicas de Artesanía.",
						"Cuando aprendes un nuevo nivel de técnicas de artesanía, aplicas una técnica de ese nivel a una pieza de equipo de maestría sin coste alguno, aunque debes seguir pagando los materiales adicionales requeridos en la descripción de la técnica, si los hubiera."
					]
				},
				{
					"type": "entries",
					"name": "Crafting Ability",
					"entries": [
						"La inteligencia es tu habilidad principal cuando se trata de la artesanía. Además, utilizas tu modificador de Inteligencia cuando estableces la DC de la tirada de salvación cuando una Técnica de Artesanía lo requiere.",
						{
							"type": "abilityDc",
							"name": "Crafting technique",
							"attributes": [
								"int"
							]
						}
					]
				},
				{
					"type": "inset",
					"name": "Crafting",
					"entries": [
						"La habilidad de forjar y crear objetos es fundamental para el artesano. Para crear un objeto, un personaje necesita tres cosas: materiales, herramientas y tiempo:",
						{
							"type": "list",
							"items": [
								"En la mayoría de los casos, la materia prima de un objeto puede obtenerse por la mitad del precio del mismo. Este coste puede fluctuar en función de las circunstancias actuales del personaje, sus contactos o el acceso a los recursos naturales.",
								"Por lo general, todo lo que se necesita para fabricar un objeto es un conjunto de herramientas artesanales adecuadas y el dominio de su uso, aunque a veces se necesita un taller más grande para objetos más complejos, y un andamiaje adecuado y equipo de movimiento de tierras para la construcción de edificios y muros.",
								"El tiempo necesario para fabricar un objeto se mide en función de su valor en el mercado. Normalmente, un personaje progresa en la elaboración de un objeto igual a 5 gp por cada día de inactividad, completando su trabajo cuando esta cantidad supera el precio del objeto. Como artesano, trabajas mucho más rápido y haces un progreso igual a 50 gp × tu nivel de artesano cada día."
							]
						}
					]
				}
			]
		},
		{
			"name": "Tool Belt",
			"source": "mfovc",
			"className": "Craftsman",
			"classSource": "mfovc",
			"level": 2,
			"entries": [
				"Mientras que otros aventureros pueden confiar en los hechizos, en la suerte o en la fuerza bruta para resolver un problema, tú crees en tener siempre la herramienta adecuada a mano. A partir del 2º nivel, puedes utilizar tu acción para recuperar una pieza de equipo no mágico de tu cinturón, delantal, mochila, carro o cualquier otro lugar en el que guardes tus herramientas, incluso si no lo tenías antes en tu inventario. El precio de este objeto en gp no debe ser superior a 5 veces tu nivel de artesano. Los objetos recuperados de esta manera permanecen en tu inventario hasta que tomes un descanso largo.",
				"Puedes usar esta habilidad un número de veces igual a tu modificador de Inteligencia, y recuperas todos los usos gastados cuando terminas un descanso largo."
			]
		},
		{
			"name": "Profession",
			"source": "mfovc",
			"className": "Craftsman",
			"classSource": "mfovc",
			"level": 3,
			"entries": [
				"A 3er nivel, eliges tu especialización en artesanía. Selecciona una de las profesiones de la lista que aparece a continuación; obtienes la habilidad de 3er nivel de esa profesión. Obtienes una habilidad de Profesión adicional a 7º, 10º, 14º y 18º nivel."
			]
		},
		{
			"name": "Ability Score Improvement",
			"source": "mfovc",
			"className": "Craftsman",
			"classSource": "mfovc",
			"level": 4,
			"entries": [
				"Al alcanzar el 4º nivel, puedes aumentar una puntuación de habilidad de tu elección en 2, o puedes aumentar dos puntuaciones de habilidad de tu elección en 1. Como es normal, no puedes aumentar una puntuación de habilidad por encima de 20 utilizando este rasgo.",
				"Si tu DM permite el uso de hazañas, puedes tomar una hazaña en su lugar."
			]
		},
		{
			"name": "Extra Attack",
			"source": "mfovc",
			"className": "Craftsman",
			"classSource": "mfovc",
			"level": 5,
			"entries": [
				"A partir del 5º nivel, puedes atacar dos veces, en lugar de una, siempre que realices la acción de Ataque en tu turno."
			]
		},
		{
			"name": "Folded Steel",
			"source": "mfovc",
			"className": "Craftsman",
			"classSource": "mfovc",
			"level": 6,
			"entries": [
				"A 6º nivel, descubres o creas nuevos procesos para hacer que tu equipo de trabajo maestro sea aún más fuerte que antes. Las armas maestras y exóticas creadas por ti cuentan como mágicas a efectos de superar la resistencia al daño y la inmunidad."
			]
		},
		{
			"name": "Apprentice Techniques",
			"source": "mfovc",
			"className": "Craftsman",
			"classSource": "mfovc",
			"level": 6,
			"entries": [
				"A 6º nivel, puedes modificar objetos de maestría con técnicas de Aprendiz."
			]
		},
		{
			"name": "Profession Feature",
			"source": "mfovc",
			"className": "Craftsman",
			"classSource": "mfovc",
			"level": 7,
			"entries": [
				"A 7º nivel, obtienes un rasgo de tu profesión de artesano."
			]
		},
		{
			"name": "Ability Score Improvement",
			"source": "mfovc",
			"className": "Craftsman",
			"classSource": "mfovc",
			"level": 8,
			"entries": [
				"Al alcanzar el 8º nivel, puedes aumentar una puntuación de habilidad a tu elección en 2, o puedes aumentar dos puntuaciones de habilidad a tu elección en 1. Como es normal, no puedes aumentar una puntuación de habilidad por encima de 20 utilizando este rasgo.",
				"Si tu DM permite el uso de hazañas, puedes tomar una hazaña en su lugar."
			]
		},
		{
			"name": "Layman's Modifications",
			"source": "mfovc",
			"className": "Craftsman",
			"classSource": "mfovc",
			"level": 9,
			"entries": [
				"A partir del 9º nivel, aprendes a generalizar tus técnicas de artesanía para otros. El equipo de maestría que hayas modificado sólo con técnicas de principiante puede ser utilizado de forma competente por otros."
			]
		},
		{
			"name": "Journeyman Techniques",
			"source": "mfovc",
			"className": "Craftsman",
			"classSource": "mfovc",
			"level": 9,
			"entries": [
				"A 9º nivel, puedes modificar objetos de maestría con técnicas de Journeyman."
			]
		},
		{
			"name": "Profession Feature",
			"source": "mfovc",
			"className": "Craftsman",
			"classSource": "mfovc",
			"level": 10,
			"entries": [
				"A 10º nivel, obtienes un rasgo de tu profesión de artesano."
			]
		},
		{
			"name": "Craftman's Strike",
			"source": "mfovc",
			"className": "Craftsman",
			"classSource": "mfovc",
			"level": 11,
			"entries": [
				"Has aprendido a construir, pero también sabes cómo destruir. A 11º nivel, una vez por turno, puedes añadir {@dice 1d8} de daño a un ataque que realices contra un objeto, constructo o criatura que lleve armadura fabricada, y tus ataques siempre superan el umbral de daño de un objeto."
			]
		},
		{
			"name": "Ability Score Improvement",
			"source": "mfovc",
			"className": "Craftsman",
			"classSource": "mfovc",
			"level": 12,
			"entries": [
				"Cuando alcanzas el nivel 12, puedes aumentar una puntuación de habilidad de tu elección en 2, o puedes aumentar dos puntuaciones de habilidad de tu elección en 1. Como es normal, no puedes aumentar una puntuación de habilidad por encima de 20 utilizando este rasgo.",
				"Si tu DM permite el uso de hazañas, puedes tomar una hazaña en su lugar."
			]
		},
		{
			"name": "Master Techniques",
			"source": "mfovc",
			"className": "Craftsman",
			"classSource": "mfovc",
			"level": 13,
			"entries": [
				"A 13º nivel, puedes modificar los objetos de maestría con técnicas de maestría."
			]
		},
		{
			"name": "Profession Feature",
			"source": "mfovc",
			"className": "Craftsman",
			"classSource": "mfovc",
			"level": 14,
			"entries": [
				"A nivel 14, obtienes un rasgo de tu profesión de artesano."
			]
		},
		{
			"name": "Uncanny Tool Belt",
			"source": "mfovc",
			"className": "Craftsman",
			"classSource": "mfovc",
			"level": 15,
			"entries": [
				"Tienes un don para encontrar las cosas más útiles enterradas en tu carro. A partir del 15º nivel, puedes producir un único objeto mágico poco común de tu cinturón de herramientas. El objeto permanece en tu poder hasta que tomes un descanso corto o largo. Una vez que utilizas esta habilidad, debes tomar un descanso largo antes de poder hacerlo de nuevo."
			]
		},
		{
			"name": "Ability Score Improvement",
			"source": "mfovc",
			"className": "Craftsman",
			"classSource": "mfovc",
			"level": 16,
			"entries": [
				"Cuando alcanzas el nivel 16, puedes aumentar una puntuación de habilidad a tu elección en 2, o puedes aumentar dos puntuaciones de habilidad a tu elección en 1. Como es normal, no puedes aumentar una puntuación de habilidad por encima de 20 utilizando esta característica.",
				"Si tu DM permite el uso de hazañas, puedes tomar una hazaña en su lugar."
			]
		},
		{
			"name": "Legendary Techniques",
			"source": "mfovc",
			"className": "Craftsman",
			"classSource": "mfovc",
			"level": 17,
			"entries": [
				"A 17º nivel, puedes modificar objetos de trabajo maestro con técnicas legendarias."
			]
		},
		{
			"name": "Profession Feature",
			"source": "mfovc",
			"className": "Craftsman",
			"classSource": "mfovc",
			"level": 18,
			"entries": [
				"A nivel 18, obtienes un rasgo de tu profesión de artesano."
			]
		},
		{
			"name": "Ability Score Improvement",
			"source": "mfovc",
			"className": "Craftsman",
			"classSource": "mfovc",
			"level": 19,
			"entries": [
				"Al alcanzar el nivel 19, puedes aumentar una puntuación de habilidad a tu elección en 2, o puedes aumentar dos puntuaciones de habilidad a tu elección en 1. Como es normal, no puedes aumentar una puntuación de habilidad por encima de 20 utilizando esta característica.",
				"Si tu DM permite el uso de hazañas, puedes tomar una hazaña en su lugar."
			]
		},
		{
			"name": "Magnum Opus",
			"source": "mfovc",
			"className": "Craftsman",
			"classSource": "mfovc",
			"level": 20,
			"entries": [
				"A 20º nivel, completas un objeto de una majestuosidad sin igual. Puedes retirarte a tu forja durante un periodo de 30 días; durante este tiempo, trabajas febrilmente. Al final de los 30 días, sales de tu forja con tu creación: un único objeto mágico legendario que puedes sintonizar. Este objeto está ligado a tu propia alma: independientemente del tipo, siempre se considera que estás sintonizado con él, y ninguna otra criatura puede sintonizarlo mientras estés vivo. Además, mientras estés en el mismo plano de existencia que tu objeto, puedes llamarlo a tu mano o a tu cuerpo (según sea el caso). Sólo puedes crear un Magnum Opus una vez."
			]
		}
	],
	"subclassFeature": [
		{
			"name": "Beginner Techniques",
			"source": "mfovc",
			"className": "Craftsman",
			"classSource": "mfovc",
			"subclassShortName": "Techniques",
			"subclassSource": "mfovc",
			"level": 2,
			"entries": [
				{
					"type": "refSubclassFeature",
					"subclassFeature": "Aerodynamic|Craftsman|mfovc|Techniques|mfovc|2"
				},
				{
					"type": "refSubclassFeature",
					"subclassFeature": "Cleats|Craftsman|mfovc|Techniques|mfovc|2"
				},
				{
					"type": "refSubclassFeature",
					"subclassFeature": "Collapsible|Craftsman|mfovc|Techniques|mfovc|2"
				},
				{
					"type": "refSubclassFeature",
					"subclassFeature": "Double|Craftsman|mfovc|Techniques|mfovc|2"
				},
				{
					"type": "refSubclassFeature",
					"subclassFeature": "Hollow|Craftsman|mfovc|Techniques|mfovc|2"
				},
				{
					"type": "refSubclassFeature",
					"subclassFeature": "Piton Armor|Craftsman|mfovc|Techniques|mfovc|2"
				},
				{
					"type": "refSubclassFeature",
					"subclassFeature": "Mighty|Craftsman|mfovc|Techniques|mfovc|2"
				},
				{
					"type": "refSubclassFeature",
					"subclassFeature": "Modular|Craftsman|mfovc|Techniques|mfovc|2"
				},
				{
					"type": "refSubclassFeature",
					"subclassFeature": "Retractable Shield|Craftsman|mfovc|Techniques|mfovc|2"
				},
				{
					"type": "refSubclassFeature",
					"subclassFeature": "Thorn Armor|Craftsman|mfovc|Techniques|mfovc|2"
				},
				{
					"type": "refSubclassFeature",
					"subclassFeature": "Switch Weapon|Craftsman|mfovc|Techniques|mfovc|2"
				},
				{
					"type": "refSubclassFeature",
					"subclassFeature": "Weighted|Craftsman|mfovc|Techniques|mfovc|2"
				}
			]
		},
		{
			"type": "inset",
			"name": "Aerodynamic",
			"entries": [
				"{@b Components.} Arma ligera Masterwork",
				"Al añadir pesos de equilibrio adecuados, aletas estabilizadoras y redondear los bordes ásperos, te permite lanzar tu arma con precisión. Esta arma adquiere la propiedad Lanzamiento, con un alcance de (20/60)."
			],
			"source": "mfovc",
			"className": "Craftsman",
			"classSource": "mfovc",
			"subclassShortName": "Techniques",
			"subclassSource": "mfovc",
			"level": 2,
			"header": 1
		},
		{
			"type": "inset",
			"name": "Cleats",
			"entries": [
				"{@b Components.} Armadura de obra maestra",
				"Instalas un conjunto de pinchos en la parte delantera y trasera de las botas de tu armadura, lo que te proporciona una notable tracción incluso en los terrenos más difíciles. Mientras lleves esta armadura, ignorarás los terrenos difíciles no mágicos y tendrás ventaja en las tiradas de salvación para evitar que te muevan contra tu voluntad (por ejemplo, si te empujan) o para evitar que te derriben."
			],
			"source": "mfovc",
			"className": "Craftsman",
			"classSource": "mfovc",
			"subclassShortName": "Techniques",
			"subclassSource": "mfovc",
			"level": 2,
			"header": 1
		},
		{
			"type": "inset",
			"name": "Collapsible",
			"entries": [
				"{@b Components.} Arma maestra",
				"Vacías partes de tu arma, lo que te permite replegarla sobre sí misma y hacerla más fácil de ocultar. Tu arma adquiere la propiedad Colapsable."
			],
			"source": "mfovc",
			"className": "Craftsman",
			"classSource": "mfovc",
			"subclassShortName": "Techniques",
			"subclassSource": "mfovc",
			"level": 2,
			"header": 1
		},
		{
			"type": "inset",
			"name": "Double",
			"entries": [
				"{@b Components.} Dos armas maestras que no sean pesadas ni de dos manos",
				"Unes dos armas maestras en el pomo, forjando una única arma de doble filo. El arma resultante gana las propiedades de dos manos y doble, y utiliza cada uno de los dados de daño de las armas combinadas (si cualquiera de las dos armas era versátil, utiliza el dado de daño de una mano)."
			],
			"source": "mfovc",
			"className": "Craftsman",
			"classSource": "mfovc",
			"subclassShortName": "Techniques",
			"subclassSource": "mfovc",
			"level": 2,
			"header": 1
		},
		{
			"type": "inset",
			"name": "Hollow",
			"entries": [
				"{@b Components.} Arma maestra de combate cuerpo a cuerpo que no es ligera",
				"Aleas una pequeña cantidad de adamantina en el acero de tu arma o la esculpes de un duramen imposiblemente resistente, y luego ahuecas la hoja o la empuñadura. Un arma hueca pesa la mitad de lo que pesaba antes, se convierte en un arma ligera y fina, y pierde la propiedad Pesada si la tenía. Todos los dados de daño de un arma hueca disminuyen en 1 paso ({@dice d12}/{@dice 2d6} -> {@dice d10} -> {@dice d8} -> {@dice d6} -> {@dice d4}), hasta un mínimo de {@dice 1d4}."
			],
			"source": "mfovc",
			"className": "Craftsman",
			"classSource": "mfovc",
			"subclassShortName": "Techniques",
			"subclassSource": "mfovc",
			"level": 2,
			"header": 1
		},
		{
			"type": "inset",
			"name": "Piton Armor",
			"entries": [
				"{@b Components.} Armadura ligera o media Masterwork",
				"Añades una serie de discretos ganchos retráctiles a los guanteletes y las botas de tu armadura. Mientras llevas esta armadura, ganas una velocidad de ascenso igual a tu velocidad de movimiento."
			],
			"source": "mfovc",
			"className": "Craftsman",
			"classSource": "mfovc",
			"subclassShortName": "Techniques",
			"subclassSource": "mfovc",
			"level": 2,
			"header": 1
		},
		{
			"type": "inset",
			"name": "Mighty",
			"entries": [
				"{@b Components.} Arco o ballesta de obra maestra",
				"Incrustas tiras de metal fuertes, aunque ligeramente flexibles, sobre los brazos de tu arco, aumentando su fuerza de tiro. Un arco poderoso aumenta su dado de daño en un paso, pero requiere que uses tu modificador de Fuerza en lugar de tu modificador de Destreza para las tiradas de ataque y daño."
			],
			"source": "mfovc",
			"className": "Craftsman",
			"classSource": "mfovc",
			"subclassShortName": "Techniques",
			"subclassSource": "mfovc",
			"level": 2,
			"header": 1
		},
		{
			"type": "inset",
			"name": "Modular",
			"entries": [
				"{@b Components.} Armadura de obra maestra",
				"Modificas tu armadura para que sea ajustable sobre la marcha. Como acción, puedes reajustar, quitar o colocar partes de tu armadura; al hacerlo, puedes cambiar tu traje entre las formas de armadura ligera (cuero tachonado), media (media placa) o pesada (placa completa).",
				"Puedes aplicar técnicas de artesanía adicionales a cada una de las formas de la armadura modular como si fueran armaduras independientes. Sin embargo, solo puedes aplicar una técnica de artesanía, además de esta, a cada forma.",
				"Aplicar esta técnica a cualquier tipo de armadura que no sea de placas completas requiere materiales adicionales: 1500 gp para una armadura ligera, 1000 gp para una armadura media y 500 gp para una armadura pesada."
			],
			"source": "mfovc",
			"className": "Craftsman",
			"classSource": "mfovc",
			"subclassShortName": "Techniques",
			"subclassSource": "mfovc",
			"level": 2,
			"header": 1
		},
		{
			"type": "inset",
			"name": "Retractable Shield",
			"entries": [
				"{@b Components.} Armadura media o pesada Masterwork y un escudo que no sea exótico",
				"Instalas un escudo retráctil en uno de tus brazaletes. Como acción adicional, puedes desplegar o retraer tu escudo. Puedes encantar este escudo o instalar cualquier otro escudo mágico en su lugar. Cuando este arma está guardada, tienes ventaja en todos los chequeos de Destreza (Juego de manos) realizados para ocultarlo."
			],
			"source": "mfovc",
			"className": "Craftsman",
			"classSource": "mfovc",
			"subclassShortName": "Techniques",
			"subclassSource": "mfovc",
			"level": 2,
			"header": 1
		},
		{
			"type": "inset",
			"name": "Thorn Armor",
			"entries": [
				"{@b Components.} Armadura media o pesada Masterwork",
				"Añades una capa de pinchos retráctiles a las rodillas, hombros, guanteletes, casco y botas de tu armadura. Mientras lleves esta armadura, tus golpes sin armas infligen un {@dice 1d4} de daño perforante. Además, cada vez que empiezas tu turno agarrando a otra criatura, ésta recibe un {@dice 1d4} de daño perforante."
			],
			"source": "mfovc",
			"className": "Craftsman",
			"classSource": "mfovc",
			"subclassShortName": "Techniques",
			"subclassSource": "mfovc",
			"level": 2,
			"header": 1
		},
		{
			"type": "inset",
			"name": "Switch Weapon",
			"entries": [
				"{@b Components.} Dos armas de trabajo maestro o un arma de trabajo maestro y dos armas de trabajo ligero cuerpo a cuerpo",
				"Tu arma adquiere una forma alternativa y se convierte en un arma intercambiable. Esta forma alternativa puede ser cualquier otra arma no mágica que no sea ya un arma intercambiable, o puede ser un par de armas ligeras no mágicas. Puedes cambiar entre las formas de tu arma como acción adicional.",
				"Puedes aplicar técnicas de artesanía adicionales a cada una de las formas del arma de cambio como si fueran armas independientes. Sin embargo, solo puedes aplicar una técnica de artesanía, además de esta, a cada forma."
			],
			"source": "mfovc",
			"className": "Craftsman",
			"classSource": "mfovc",
			"subclassShortName": "Techniques",
			"subclassSource": "mfovc",
			"level": 2,
			"header": 1
		},
		{
			"type": "inset",
			"name": "Weighted",
			"entries": [
				"{@b Components.} Arma cuerpo a cuerpo Masterwork",
				"Aleas una medida de plomo en el acero de tu arma o incrustas un núcleo de acero en su empuñadura. Un arma pesada pesa el doble de lo que pesaba antes, se convierte en un arma pesada y pierde las propiedades de Luz o Finura si las tenía. Un arma pesada con esta técnica se convierte en un arma superpesada. Todos los dados de daño de un arma pesada aumentan en 1 paso ({@dice d4} -> {@dice d6} -> {@dice d8} -> {@dice d10} -> {@dice d12}), hasta un máximo de {@dice 1d12}."
			],
			"source": "mfovc",
			"className": "Craftsman",
			"classSource": "mfovc",
			"subclassShortName": "Techniques",
			"subclassSource": "mfovc",
			"level": 2,
			"header": 1
		},
		{
			"name": "Apprentice Techniques",
			"source": "mfovc",
			"className": "Craftsman",
			"classSource": "mfovc",
			"subclassShortName": "Techniques",
			"subclassSource": "mfovc",
			"level": 6,
			"entries": [
				{
					"type": "inset",
					"name": "Adamantine Plating",
					"entries": [
						"{@b Components.} Armadura media o pesada Masterwork",
						"Tu armadura adquiere las habilidades de una armadura de adamantina. Mientras la llevas puesta, cualquier golpe crítico contra ti se convierte en un golpe normal."
					]
				},
				{
					"type": "inset",
					"name": "Bastard",
					"entries": [
						"{@b Components.} Arma maestra de combate cuerpo a cuerpo que no sea de alcance, a dos manos o versátil",
						"Alargas la empuñadura y reajustas el equilibrio de tu arma, lo que te permite blandirla con las dos manos para aumentar su potencia. Esta arma se convierte en un arma versátil: al empuñar tu arma con dos manos, el dado de daño de tu arma aumenta un paso ({@dice d4} -> {@dice d6} -> {@dice d8} -> {@dice d10} -> {@dice d12}), hasta un máximo de {@dice 1d12}."
					]
				},
				{
					"type": "inset",
					"name": "Bladed Armor",
					"entries": [
						"{@b Components.} Armadura de obra maestra",
						"Instalas un par de cuchillas retráctiles en los brazaletes de tu armadura. Estas cuchillas son armas ligeras y finas que infligen {@dice 1d4} de daño cortante o perforante. No puedes ser desarmado de estas cuchillas, y tienes ventaja en los chequeos de Destreza (Juego de manos) realizados para ocultarlas. Puedes sostener o manipular un arma, escudo u otro objeto en el mismo brazo que tus cuchillas de brazo, aunque no puedes atacar con una cuchilla de brazo y usar un objeto o arma sostenida en esa mano en el mismo turno. También puedes aplicar una técnica de artesanía a estos brazaletes."
					]
				},
				{
					"type": "inset",
					"name": "Boomerang",
					"entries": [
						"{@b Components.} Arma maestra con la propiedad Lanzar",
						"Al alterar ligeramente la forma de esta arma, permite a los usuarios especialmente hábiles devolverla a las manos que la esperan. Un arma con esta técnica adquiere la propiedad Retorno."
					]
				},
				{
					"type": "inset",
					"name": "Chained",
					"entries": [
						"{@b Components.} Arma ligera de combate cuerpo a cuerpo de obra maestra que no es de alcance ni de dos manos",
						"Unes los eslabones de una cadena larga, ligera y flexible desde el pomo de tu arma a un brazalete especial, lo que te permite blandir tu arma en un arco largo y amplio. Esta arma se convierte en un arma de alcance. Si eres desarmado de tu arma encadenada, puedes usar una acción de bonificación para tirar de ella hacia tu mano.",
						"Una vez por turno, cuando usas la acción de ataque para atacar a una criatura con esta arma, puedes usar tu acción de bonificación para hacer un segundo ataque con esa arma contra otra criatura que esté a 5 pies del objetivo."
					]
				},
				{
					"type": "inset",
					"name": "Extended",
					"entries": [
						"{@b Components.} Arma maestra de combate cuerpo a cuerpo que no es de alcance",
						"Sustituyes el mango y la empuñadura estándar de tu arma maestra por una larga empuñadura de madera o metal. El arma gana la propiedad Alcance (10 pies), gana la propiedad de dos manos si no la tenía antes. Un arma con la propiedad de versatilidad que obtiene esta técnica utiliza su dado de daño de dos manos y pierde la propiedad de versatilidad.",
						"{@b Variant Rule: Polearms.}",
						"A efectos de las hazañas y habilidades, cualquier arma a dos manos o versátil que sea funcionalmente similar a un báculo, una pica, un glaive o una alabarda se trata como si fuera una de esas armas. Esto incluye (pero no se limita a) la lanza, la gran lanza, la pica de guerra y cualquier arma con la técnica de artesanía extendida."
					]
				},
				{
					"type": "inset",
					"name": "Hardened",
					"entries": [
						"{@b Components.} Armadura pesada Masterwork",
						"Aprendes a aumentar la dureza de tu acero. Mientras llevas esta armadura, reduces en 2 el daño contundente, perforante y cortante que recibes de armas no mágicas. Esta reducción no se acumula con otras formas de reducción de daño, pero sí con la resistencia al daño."
					]
				},
				{
					"type": "inset",
					"name": "Hooked",
					"entries": [
						"{@b Components.} Arma cuerpo a cuerpo Masterwork",
						"Tu arma termina con un gancho largo y curvado, o tiene un gancho que sobresale de un extremo. Cuando golpeas a una criatura con un arma con gancho, en lugar de infligirle daño, puedes intentar empujar a la criatura hacia abajo. Cuando lo hagas, harás el chequeo con ventaja."
					]
				},
				{
					"type": "inset",
					"name": "Juggernaut Plating",
					"entries": [
						"{@b Components.} Arma cuerpo a cuerpo Masterwork",
						"Instalas un conjunto de pesadas placas en los hombros y un casco reforzado en tu armadura, transformándote en un auténtico ariete. Mientras llevas esta armadura, puedes usar tu acción para moverte hasta tu velocidad hacia un objeto inanimado. Al final de este movimiento, golpeas el objeto, infligiendo {@dice 3d6} + dos veces tu nivel de artesano de daño contundente. Este daño ignora el umbral de daño del objeto."
					]
				},
				{
					"type": "inset",
					"name": "Mithral Plating",
					"entries": [
						"{@b Components.} Armadura media o pesada Masterwork",
						"Tu armadura adquiere las habilidades de una armadura de mithral. Una camisa o coraza de mithral puede llevarse bajo la ropa normal. Si la armadura normalmente impone desventaja a los chequeos de Destreza (Sigilo) o tiene un requisito de Fuerza, la versión de mithral de la armadura no lo hace. Esta armadura no tiene bonificación de Destreza máxima, y ya no impone ninguna penalización por dormir con ella."
					]
				},
				{
					"type": "inset",
					"name": "Sighted",
					"entries": [
						"{@b Components.} Arco o ballesta de obra maestra",
						"Instalas un juego de miras y una varilla de equilibrio en tu arco, lo que te permite hacer disparos a larga distancia con facilidad. Los ataques a larga distancia realizados con un arco con mira no tienen desventaja."
					]
				}
			]
		},
		{
			"name": "Journeyman Techniques",
			"source": "mfovc",
			"className": "Craftsman",
			"classSource": "mfovc",
			"subclassShortName": "Techniques",
			"subclassSource": "mfovc",
			"level": 9,
			"entries": [
				{
					"type": "inset",
					"name": "Darksteel Plating",
					"entries": [
						"{@b Components.} Armadura pesada Masterwork",
						"Aprendes a mezclar piedra oscura, piedra infundida con energía necrótica, en tu acero. Ganas resistencia al daño necrótico y radiante mientras llevas esta armadura."
					]
				},
				{
					"type": "inset",
					"name": "Deadblow",
					"entries": [
						"{@b Components.} Arma cuerpo a cuerpo Masterwork",
						"Se vacía una parte del arma y se rellena la cavidad con perdigones de plomo, azogue o cualquier otro material pesado y fluido. El peso del arma, aunque ahora está algo desequilibrada, se desplaza constantemente, y un golpe rápido desplazará el material del interior hacia delante, aumentando la fuerza del impacto. Cuando golpeas a una criatura con esta arma, le infliges un {@dice 1d6} de daño adicional y el objetivo debe realizar una tirada de salvación de Fuerza o ser empujado a 1,5 metros de ti. Si esta arma tiene las propiedades Luz o Finura, las pierde."
					]
				},
				{
					"type": "inset",
					"name": "Deep Crystal Studding",
					"entries": [
						"{@b Components.} Armadura ligera o media Masterwork",
						"Aprendes a tachonar tu cuero subyacente con cristal profundo, cristal infundido con energía psíquica latente. Ganas resistencia al daño de fuerza y psíquico mientras llevas esta armadura."
					]
				},
				{
					"type": "inset",
					"name": "Installed Crossbow",
					"entries": [
						"{@b Components.} Armadura de obra maestra",
						"Fijas una ballesta de mano y un mecanismo de carga a un guantelete de tu armadura. Esta ballesta de mano inflige {@dice 1d6} de daño e ignora la propiedad de carga. Tienes ventaja en los chequeos de Destreza (Juego de manos) para ocultar esta ballesta. Si lo deseas, puedes sustituir esta ballesta instalada por cualquier otra ballesta ligera o de mano, o puedes tenerla encantada. Puedes sostener o manipular un arma, escudo u otro objeto en el mismo brazo que tu ballesta instalada, aunque no puedes atacar con tu ballesta instalada y usar un objeto o arma sostenida en esa mano en el mismo turno."
					]
				},
				{
					"type": "inset",
					"name": "Installed Wand",
					"entries": [
						"{@b Components.} Armadura Masterwork, 150 gp de componentes de hechizos",
						"Aprendes a instalar una varita funcional en uno de los brazos o en una carcasa especial en el hombro de tu armadura. Mientras lleves esta armadura, puedes lanzar dos cantrips seleccionados de la lista de hechizos de mago, hechicero o brujo. Tu modificador de lanzamiento de hechizos para estos cantrips es la Inteligencia. Puedes sustituir esta varita por otra varita mágica de cualquier tipo.",
						"Puedes aplicar esta técnica a un solo traje de armadura maestra hasta 3 veces."
					]
				},
				{
					"type": "inset",
					"name": "Magnetic Plating",
					"entries": [
						"{@b Components.} Armadura pesada Masterwork",
						"Aprendes a mezclar la piedra de la armadura para atraer los ataques del enemigo hacia tu coraza impenetrable. Mientras llevas esta armadura, puedes usar un bonificador para activar o desactivar sus imanes internos. Mientras estén activos, cada vez que se realice un ataque con un arma a distancia que utilice munición metálica contra un objetivo que se encuentre a 3 metros de ti, te convertirás en el objetivo.",
						"Además, mientras tus imanes estén activos, los ataques cuerpo a cuerpo con armas de metal realizados contra ti tienen ventaja. Sin embargo, al impactar, el atacante debe realizar una tirada de salvación de Fuerza o ser desarmado de su arma, ya que se pega a tu armadura. El arma se libera cuando desactivas tus imanes internos."
					]
				},
				{
					"type": "inset",
					"name": "Magnetic Weapon",
					"entries": [
						"{@b Components.} Arma maestra",
						"Aprendes a mezclar la piedra de lodragón con tu acero, dirigiendo tus ataques hacia aquellos que se cubren de metal. Cuando atacas a una criatura que lleva una armadura compuesta principalmente de metal o que ella misma está hecha principalmente de metal (como un gólem de hierro), tienes ventaja en la tirada de ataque. Una vez que usas esta habilidad, debes terminar un descanso corto o largo antes de volver a usarla."
					]
				},
				{
					"type": "inset",
					"name": "Serrated",
					"entries": [
						"{@b Components.} Arma o armadura magistral",
						"Recortas o forjas en la hoja de tu arma unos dientes terriblemente afilados que cortan profundamente la carne desprotegida. Un arma dentada inflige un {@dice 1d8} de daño adicional a cualquier criatura que no lleve armadura fabricada y tenga una Clase de Armadura natural de 20 o menos."
					]
				},
				{
					"type": "inset",
					"name": "Shield-Guard",
					"entries": [
						"{@b Components.} Arma maestra",
						"Fabricas una amplia protección de broquel para tu arma, lo que la hace mucho más adecuada para desviar golpes mortales. Un arma con esta técnica gana la propiedad Escudo."
					]
				},
				{
					"type": "inset",
					"name": "Spiked",
					"entries": [
						"{@b Components.} Arma maestra de combate cuerpo a cuerpo que inflige daño punzante o contundente",
						"Has creado grandes y pesados pinchos en el extremo de tu arma, lo que te permite atravesar la armadura. Un arma con pinchos inflige un {@dice 1d8} de daño adicional a cualquier criatura que lleve armadura fabricada o tenga una clase de armadura natural superior a 20."
					]
				},
				{
					"type": "inset",
					"name": "Superior",
					"entries": [
						"{@b Components.} Arma o armadura magistral",
						"Puedes aplicar esta técnica a una misma pieza de equipo dos veces; la primera vez es una técnica de journeymen y la segunda es una técnica legendaria. Si se aplica a un arma, su bonificación a las tiradas de ataque y daño aumenta en 1, hasta un máximo de +3. Si se aplica a una armadura, su bonificación a la CA aumenta en 1, hasta un máximo de +3."
					]
				},
				{
					"type": "inset",
					"name": "Twinshot",
					"entries": [
						"{@b Components.} Arco o ballesta de obra maestra",
						"Colocas un conjunto especializado de montura y cuerda de arco, lo que te permite ensartar y disparar dos flechas a la vez. Una vez por turno, cuando usas la acción de ataque para realizar un ataque con tu arco, puedes realizar un segundo ataque contra otra criatura a menos de 3 metros del objetivo."
					]
				}
			]
		},
		{
			"name": "Master Techniques",
			"source": "mfovc",
			"className": "Craftsman",
			"classSource": "mfovc",
			"subclassShortName": "Techniques",
			"subclassSource": "mfovc",
			"level": 13,
			"entries": [
				{
					"type": "inset",
					"name": "Abyssal Greenstone Weapon",
					"entries": [
						"{@b Components.} Arma maestra",
						"Aprendes a mezclar la Piedra Verde Abisal, piedra del Abismo infundida con energía necrótica enfermiza, en tu acero. Tu arma inflige un {@dice 2d4} de daño de veneno adicional al impactar, y una criatura golpeada por tu arma debe hacer una tirada de salvación de Constitución o quedar envenenada hasta el comienzo de tu siguiente turno."
					]
				},
				{
					"type": "inset",
					"name": "Aquatic Plating",
					"entries": [
						"{@b Components.} Armadura de obra maestra",
						"Aprendes a mezclar la esencia elemental del agua en tu armadura, lo que permite que tu armadura se mueva sin esfuerzo en el agua. Mientras llevas esta armadura, ganas una velocidad de nado igual a tu velocidad de movimiento, ganas resistencia al daño por frío y puedes respirar bajo el agua."
					]
				},
				{
					"type": "inset",
					"name": "Cushioning Underlay",
					"entries": [
						"{@b Components.} Armadura de obra maestra",
						"Aprendes a rellenar tu armadura con plumón de búho en los puntos adecuados para resistir el daño por caída. Mientras lleves esta armadura, serás inmune al daño por caída y ganarás resistencia al daño por apaleamiento."
					]
				},
				{
					"type": "inset",
					"name": "Darksteel Weapon",
					"entries": [
						"{@b Components.} Arma maestra",
						"Aprendes a mezclar piedra oscura, piedra infundida con energía necrótica, en tu acero. Tu arma inflige un {@dice 1d8} de daño necrótico adicional al impactar."
					]
				},
				{
					"type": "inset",
					"name": "Deep Crystal Weapon",
					"entries": [
						"{@b Components.} Arma maestra",
						"Aprendes a fabricar cuchillas y cabezas de armas de cristal profundo, cristal infundido con energía psíquica latente. Tu arma inflige un {@dice 1d6} de daño de fuerza adicional al impactar."
					]
				},
				{
					"type": "inset",
					"name": "Dragon Scale Underlay",
					"entries": [
						"{@b Components.} Armadura de obra maestra",
						"Aprendes a utilizar mejor la escama de dragón en la fabricación de armaduras más pesadas. Cuando aplicas esta técnica, seleccionas dos tipos de daño entre ácido, fuego, rayo, veneno y trueno. Mientras lleves esta armadura, ganarás resistencia a esos dos tipos de daño."
					]
				},
				{
					"type": "inset",
					"name": "Infernal Bloodstone Weapon",
					"entries": [
						"{@b Components.} Arma maestra",
						"Aprendes a infundir la Piedra de Sangre Infernal, hierro forjado de los Nueve Infiernos, en tu acero. Tu arma inflige un {@dice 1d6} de daño de fuego adicional al impactar, y el objetivo debe realizar una tirada de salvación de Constitución o recibir {@dice 1d6} de daño necrótico al inicio de tu siguiente turno."
					]
				},
				{
					"type": "inset",
					"name": "Living Wood Underlay",
					"entries": [
						"{@b Components.} Armadura de obra maestra",
						"Aplicas una fina capa de madera viva en la parte inferior de tu armadura. Esta madera rezuma una savia reconstituyente en tu piel. Siempre que empieces tu turno llevando esta armadura, estés consciente y tengas menos de la mitad de tus puntos de vida máximos, recuperas un punto de vida."
					]
				},
				{
					"type": "inset",
					"name": "Molten Plating",
					"entries": [
						"{@b Components.} Armadura de obra maestra",
						"Aprendes a mezclar la esencia elemental del fuego en tu acero, filtrando el calor en tus ataques y proporcionándote protección contra el mismo. Mientras llevas esta armadura, obtienes resistencia al daño por fuego, y cada una de tus armas acopladas inflige un {@dice 1d6} de daño por fuego adicional al impactar."
					]
				},
				{
					"type": "inset",
					"name": "Primordium Steel Plating",
					"entries": [
						"{@b Components.} Arma maestra",
						"Aprendes a trabajar con el Primordium, un elemento que se extrae en las regiones que bordean los planos elementales. Cuando infliges daño con tu arma, infliges un {@dice 1d6} adicional de daño de ácido, frío, fuego o rayo, a tu elección."
					]
				},
				{
					"type": "inset",
					"name": "Solanium Truesteel Plating",
					"entries": [
						"{@b Components.} Arma maestra",
						"Aprendes a mezclar hierro solanium, piedra infundida con energía radiante, en tu acero. Tu arma inflige un {@dice 1d6} de daño radiante adicional al impactar, o un {@dice 2d6} contra demonios, diablos y muertos vivientes. Además, tu arma brilla, arrojando luz como una antorcha."
					]
				},
				{
					"type": "inset",
					"name": "Windswept Plating",
					"entries": [
						"{@b Components.} Armadura de obra maestra",
						"Aprendes a mezclar la esencia elemental del aire con tu acero, lo que permite a tu armadura casi flotar en el aire y moverse más rápido que el viento. Mientras llevas esta armadura, tu velocidad de movimiento básica aumenta en 3 metros y adquieres la capacidad de volar a tu velocidad de movimiento normal. Debes empezar y terminar tu vuelo en tierra firme; de lo contrario, caes inmediatamente."
					]
				}
			]
		},
		{
			"name": "Legendary Techniques",
			"source": "mfovc",
			"className": "Craftsman",
			"classSource": "mfovc",
			"subclassShortName": "Techniques",
			"subclassSource": "mfovc",
			"level": 17,
			"entries": [
				{
					"type": "inset",
					"name": "Immortal Plating",
					"entries": [
						"{@b Components.} Armadura de obra maestra",
						"Aprendes a mezclar esencia celestial en tu acero; esta esencia vuelve a tejer tus heridas, a un ritmo muy alarmante. Siempre que empieces tu turno llevando esta armadura, estés consciente y tengas menos de la mitad de tus puntos de golpe máximos, recuperas 4 puntos de golpe. Esta curación se acumula con la bonificación de la armadura de madera viva."
					]
				},
				{
					"type": "inset",
					"name": "Penetrating",
					"entries": [
						"{@b Components.} Arco o ballesta de obra maestra",
						"Acoplas un engranaje y un juego de poleas especializados a tu arco, lo que te permite atravesar tus objetivos. Como acción, puedes disparar una flecha, atacando a todas las criaturas en una línea de 5 pies de ancho hasta el alcance de tu arco. Haz una tirada de ataque: todas las criaturas en esta línea deben hacer una tirada de salvación de Destreza con una DC igual a tu tirada de ataque o recibirán un daño igual a {@dice 1d8} + el daño normal de tu arco, o la mitad si la salvación es exitosa."
					]
				},
				{
					"type": "inset",
					"name": "Pincer",
					"entries": [
						"{@b Components.} Arma maestra de combate cuerpo a cuerpo que inflige daño punzante",
						"Tienes un par de pinzas mecánicas alrededor de la punta de tu arma, lo que te permite atrapar a los enemigos sin esfuerzo. Cada vez que golpeas a una criatura con tu arma, puedes intentar automáticamente atraparla, utilizando tu tirada de ataque en lugar de tu chequeo de Atletismo. Si tienes éxito, la criatura queda retenida hasta que la sueltes o tenga éxito en una tirada de salvación de Fuerza para liberarse."
					]
				},
				{
					"type": "inset",
					"name": "Pulverizing",
					"entries": [
						"{@b Components.} Arma maestra de combate cuerpo a cuerpo que inflige daño contundente",
						"Equipas un pistón mecanizado en la cabeza de tu arma, aumentando su capacidad destructiva. Una vez por turno, cuando golpeas con esta arma, puedes infligir un {@dice 2d6} de daño contundente adicional o un {@dice 4d6} de daño si golpeas un objeto o un constructo."
					]
				},
				{
					"type": "inset",
					"name": "Shredding",
					"entries": [
						"{@b Components.} Arma maestra de combate cuerpo a cuerpo que inflige daño cortante",
						"Colocas dientes de sierra mecanizados en el filo de tu arma, lo que te permite infligir graves heridas a tus enemigos. Una vez por turno, cuando golpeas a una criatura con esta arma, puedes herir al objetivo. Al comienzo de cada turno de la criatura herida, recibe {@dice 1d8} de daño necrótico por cada vez que la hayas herido, y entonces puede hacer una tirada de salvación de Constitución, terminando el efecto de todas esas heridas sobre sí misma si tiene éxito. Alternativamente, la criatura herida, o una criatura a menos de 5 pies de ella, puede usar una acción para hacer un chequeo de Sabiduría (Medicina) DC 15, terminando el efecto de tales heridas en ella si tiene éxito."
					]
				}
			]
		},
		{
			"name": "Armigier",
			"source": "mfovc",
			"className": "Craftsman",
			"classSource": "mfovc",
			"subclassShortName": "Armigier",
			"subclassSource": "mfovc",
			"level": 3,
			"entries": [
				"Has dedicado tu vida al arte de la herrería de armaduras, con la firme creencia de que la placa correcta en el lugar correcto puede hacerte invencible.",
				{
					"type": "entries",
					"name": "Exotic Smithing",
					"entries": [
						"A 3er nivel, aprendes a fabricar equipo exótico. Puedes fabricar cualquier traje de armadura exótica o escudo exótico."
					]
				},
				{
					"type": "entries",
					"name": "Armor Master",
					"entries": [
						"No sólo aprendes a forjar poderosas armaduras, sino que puedes llevarlas con habilidad. A 3er nivel, obtienes uno de los siguientes estilos de lucha:",
						{
							"type": "options",
							"entries": [
								{
									"type": "entries",
									"name": "Defense",
									"entries": [
										"Mientras lleves armadura, ganas un bono de +1 a la CA."
									]
								},
								{
									"type": "entries",
									"name": "Protection",
									"entries": [
										"Cuando una criatura que puedes ver ataca a un objetivo que no eres tú y que está a menos de 1,5 metros de ti, puedes usar tu reacción para imponer desventaja en la tirada de ataque. Debes estar blandiendo un escudo."
									]
								}
							]
						}
					]
				}
			]
		},
		{
			"name": "Iconic Emblem",
			"source": "mfovc",
			"className": "Craftsman",
			"classSource": "mfovc",
			"subclassShortName": "Armigier",
			"subclassSource": "mfovc",
			"level": 7,
			"header": 2,
			"entries": [
				"A partir del 7º nivel, puedes blasonar tu armadura y escudo con un símbolo personal, uno que sea conocido por muchos para representar la artesanía y el valor. Una criatura que te vea puede identificarte con un chequeo de Inteligencia DC 12. Cuando un aliado que pueda verte haga una tirada de salvación en la que no sea competente, puede añadir la mitad de tu bonificación de competencia (redondeada hacia arriba) a la salvación."
			]
		},
		{
			"name": "Armigier's Eye",
			"source": "mfovc",
			"className": "Craftsman",
			"classSource": "mfovc",
			"subclassShortName": "Armigier",
			"subclassSource": "mfovc",
			"level": 10,
			"header": 2,
			"entries": [
				"A partir del 10º nivel, puedes dedicar 10 minutos a reforzar una armadura, o hasta 6 tras un descanso corto o largo, que gana una de las siguientes propiedades a tu elección:",
				{
					"type": "options",
					"entries": [
						{
							"type": "entries",
							"name": "Adamant",
							"entries": [
								"Cuando una criatura que lleva esta armadura recibe daño, reduce la cantidad que recibe en un {@dice 1d8}."
							]
						},
						{
							"type": "entries",
							"name": "Bandana",
							"entries": [
								"Una criatura que lleve esta armadura tiene un bono de +1 a la Clase de Armadura."
							]
						}
					]
				},
				"Esta armadura conserva su refuerzo hasta que la criatura que la lleva es golpeada. Entonces, la armadura deja de estar reforzada."
			]
		},
		{
			"name": "Wall of Iron",
			"source": "mfovc",
			"className": "Craftsman",
			"classSource": "mfovc",
			"subclassShortName": "Armigier",
			"subclassSource": "mfovc",
			"level": 14,
			"header": 2,
			"entries": [
				"A partir del 14º nivel, como acción adicional en tu turno, puedes ganar resistencia al daño contundente, perforante y cortante hasta el final de tu siguiente turno. Una vez que usas esta habilidad, debes terminar un descanso corto o largo antes de poder usarla de nuevo."
			]
		},
		{
			"name": "Master Armorsmith",
			"source": "mfovc",
			"className": "Craftsman",
			"classSource": "mfovc",
			"subclassShortName": "Armigier",
			"subclassSource": "mfovc",
			"level": 18,
			"header": 2,
			"entries": [
				"A 18º nivel, alcanzas la cima de tu oficio. Aprendes la siguiente técnica de artesanía, que puedes aplicar inmediatamente a un traje de armadura magistral:",
				{
					"type": "inset",
					"name": "Invincible Plating",
					"entries": [
						"{@i Legendary technique}",
						"{@b Components.} Armadura pesada Masterwork",
						"Aprendes a mezclar la esencia del Elemento Tierra con tu acero, lo que hace que tu armadura sea casi indestructible a ciertas formas de golpe. Elige entre daño contundente, perforante o cortante. Mientras lleves esa armadura, serás inmune a ese tipo de daño."
					]
				}
			]
		},
		{
			"name": "Weaponsmith",
			"source": "mfovc",
			"className": "Craftsman",
			"classSource": "mfovc",
			"subclassShortName": "Weaponsmith",
			"subclassSource": "mfovc",
			"level": 3,
			"entries": [
				"Hoja y arco, hacha y maza: son las herramientas con las que intentas cambiar el mundo. Crees que la hoja adecuada, en la mano adecuada, puede hacerte imparable.",
				{
					"type": "entries",
					"name": "Exotic Smithing",
					"entries": [
						"A 3er nivel, aprendes a fabricar equipo exótico. Puedes fabricar cualquier tipo de arma exótica."
					]
				},
				{
					"type": "entries",
					"name": "Weapon Master",
					"entries": [
						"No sólo forjas grandes armas, también luchas con ellas. A 3er nivel, obtienes uno de los siguientes estilos de lucha:",
						{
							"type": "options",
							"entries": [
								{
									"type": "entries",
									"name": "Archery",
									"entries": [
										"Obtienes un bono de +2 a las tiradas de ataque que hagas con armas a distancia."
									]
								},
								{
									"type": "entries",
									"name": "Dueling",
									"entries": [
										"Cuando estés empuñando un arma de cuerpo a cuerpo en una mano y ninguna otra arma, ganas un bono de +2 a las tiradas de daño con esa arma."
									]
								},
								{
									"type": "entries",
									"name": "Great Weapon Fighting",
									"entries": [
										"Cuando sacas un 1 o un 2 en un dado de daño para un ataque que realizas con un arma cuerpo a cuerpo que manejas con dos manos, puedes volver a tirar el dado y debes utilizar la nueva tirada, incluso si la nueva tirada es un 1 o un 2. El arma debe tener la propiedad de dos manos o versátil para que obtengas este beneficio."
									]
								}
							]
						}
					]
				}
			]
		},
		{
			"name": "Wicked Blade",
			"source": "mfovc",
			"className": "Craftsman",
			"classSource": "mfovc",
			"subclassShortName": "Weaponsmith",
			"subclassSource": "mfovc",
			"level": 7,
			"header": 2,
			"entries": [
				"A 7º nivel, tus armas diabólicamente inteligentes se han ganado una reputación. Puedes añadir el doble de tu bonificación de competencia a los chequeos de Carisma (Intimidación) que realices utilizando una de tus armas maestras."
			]
		},
		{
			"name": "Armigier's Eye",
			"source": "mfovc",
			"className": "Craftsman",
			"classSource": "mfovc",
			"subclassShortName": "Weaponsmith",
			"subclassSource": "mfovc",
			"level": 10,
			"header": 2,
			"entries": [
				"A partir del 10º nivel, puedes dedicar 10 minutos a fortificar un arma, o hasta 6 tras un descanso corto o largo, que gana una de las siguientes propiedades a tu elección:",
				{
					"type": "options",
					"entries": [
						{
							"type": "entries",
							"name": "Honed",
							"entries": [
								"Esta arma tiene un bono de +2 a las tiradas de ataque."
							]
						},
						{
							"type": "entries",
							"name": "Sharpened",
							"entries": [
								"Esta arma inflige un {@dice 1d8} de daño adicional en un golpe."
							]
						}
					]
				},
				"Esta arma conserva su fortificación hasta que alcanza un objetivo. Entonces, el arma deja de estar fortificada."
			]
		},
		{
			"name": "Sundering Strike",
			"source": "mfovc",
			"className": "Craftsman",
			"classSource": "mfovc",
			"subclassShortName": "Weaponsmith",
			"subclassSource": "mfovc",
			"level": 14,
			"header": 2,
			"entries": [
				"A partir del 14º nivel, puedes utilizar tu conocimiento de los puntos débiles de las armas y armaduras para golpearlas e inutilizarlas. Como acción en tu turno, puedes realizar un único ataque contra un enemigo, apuntando a su arma o armadura e intentando destrozarla. Si aciertas, esa criatura debe tener éxito en una tirada de salvación de Destreza con una DC igual a tu DC de Artesanía. Si fallas, el objeto se rompe y queda inutilizado hasta que se arregle. Una vez que usas esta habilidad, debes terminar un descanso corto o largo antes de poder hacerlo de nuevo."
			]
		},
		{
			"name": "Master Weaponsmith",
			"source": "mfovc",
			"className": "Craftsman",
			"classSource": "mfovc",
			"subclassShortName": "Weaponsmith",
			"subclassSource": "mfovc",
			"level": 18,
			"header": 2,
			"entries": [
				"A 18º nivel, alcanzas la cima de tu arte. Aprendes la siguiente técnica de artesanía, que puedes aplicar inmediatamente a un arma maestra:",
				{
					"type": "inset",
					"name": "Devastating",
					"entries": [
						"{@i Legendary technique}",
						"{@b Components.} Arma maestra",
						"Tu arma maestra inflige un daño adicional al impactar igual a tu bono de Inteligencia."
					]
				}
			]
		}
	],
	"subclass": [
		{
			"name": "Techniques",
			"subclassFeatures": [
				"Beginner Techniques|Craftsman|mfovc|Techniques|mfovc|2",
				"Apprentice Techniques|Craftsman|mfovc|Techniques|mfovc|6",
				"Journeyman Techniques|Craftsman|mfovc|Techniques|mfovc|9",
				"Master Techniques|Craftsman|mfovc|Techniques|mfovc|13",
				"Legendary Techniques|Craftsman|mfovc|Techniques|mfovc|17"
			],
			"source": "mfovc",
			"shortName": "Techniques",
			"className": "Craftsman",
			"classSource": "mfovc"
		},
		{
			"name": "Armigier",
			"subclassFeatures": [
				"Armigier|Craftsman|mfovc|Armigier|mfovc|3",
				"Iconic Emblem|Craftsman|mfovc|Armigier|mfovc|7",
				"Armigier's Eye|Craftsman|mfovc|Armigier|mfovc|10",
				"Wall of Iron|Craftsman|mfovc|Armigier|mfovc|14",
				"Master Armorsmith|Craftsman|mfovc|Armigier|mfovc|18"
			],
			"source": "mfovc",
			"shortName": "Armigier",
			"className": "Craftsman",
			"classSource": "mfovc"
		},
		{
			"name": "Weaponsmith",
			"subclassFeatures": [
				"Weaponsmith|Craftsman|mfovc|Weaponsmith|mfovc|3",
				"Wicked Blade|Craftsman|mfovc|Weaponsmith|mfovc|7",
				"Armigier's Eye|Craftsman|mfovc|Weaponsmith|mfovc|10",
				"Sundering Strike|Craftsman|mfovc|Weaponsmith|mfovc|14",
				"Master Weaponsmith|Craftsman|mfovc|Weaponsmith|mfovc|18"
			],
			"source": "mfovc",
			"shortName": "Weaponsmith",
			"className": "Craftsman",
			"classSource": "mfovc"
		}
	]
}
